skyrl_gym/__init__.py
skyrl_gym/core.py
skyrl_gym/error.py
skyrl_gym/envs/__init__.py
skyrl_gym/envs/base_text_env.py
skyrl_gym/envs/registration.py
skyrl_gym/envs/gsm8k/env.py
skyrl_gym/envs/gsm8k/utils.py
skyrl_gym/envs/lcb/env.py
skyrl_gym/envs/lcb/livecodebench.py
skyrl_gym/envs/search/env.py
skyrl_gym/envs/search/utils.py
skyrl_gym/envs/searchcode/env.py
skyrl_gym/envs/sql/env.py
skyrl_gym/envs/sql/utils.py
skyrl_gym/tools/__init__.py
skyrl_gym/tools/core.py
skyrl_gym/tools/python.py
skyrl_gym/tools/search.py
skyrl_gym/tools/sql.py
skyrl_gym-0.1.1.dist-info/METADATA
skyrl_gym-0.1.1.dist-info/WHEEL
skyrl_gym-0.1.1.dist-info/top_level.txt
skyrl_gym-0.1.1.dist-info/RECORD
