Metadata-Version: 2.4
Name: skyrl-gym
Version: 0.1.1
Summary: RL environments for LLMs implemented with the Gymnasium API.
Author: NovaSkyAI AI Team
License: MIT
Project-URL: Repository, https://github.com/NovaSky-AI/SkyRL
Requires-Python: >=3.10
Requires-Dist: func_timeout
Requires-Dist: pandas
Requires-Dist: requests
Requires-Dist: omegaconf
Provides-Extra: dev
Requires-Dist: pytest; extra == "dev"
